CHANGES.txt
LICENSE.txt
MANIFEST.in
README.txt
sample-weighmail.ini
setup.py
weighmail/__init__.py
weighmail/config.py
weighmail/core.py
weighmail/main.py
weighmail/utils.py
weighmail.egg-info/PKG-INFO
weighmail.egg-info/SOURCES.txt
weighmail.egg-info/dependency_links.txt
weighmail.egg-info/entry_points.txt
weighmail.egg-info/requires.txt
weighmail.egg-info/top_level.txt
weighmail/observers/__init__.py
weighmail/observers/console.py
weighmail/tests/__init__.py
weighmail/tests/test_core.py
weighmail/tests/test_utils.py