Metadata-Version: 1.1
Name: weighmail
Version: 0.1.0
Summary: Labels your Gmail messages according to size.
Home-page: https://bitbucket.org/bgneal/weighmail/
Author: Brian Neal
Author-email: bgneal@gmail.com
License: BSD
Platform: UNKNOWN
Classifier: Development Status :: 3 - Alpha
Classifier: Environment :: Console
Classifier: Intended Audience :: End Users/Desktop
Classifier: License :: OSI Approved :: BSD License
Classifier: Operating System :: OS Independent
Classifier: Natural Language :: English
Classifier: Programming Language :: Python
Classifier: Programming Language :: Python :: 2.7
Classifier: Topic :: Internet
Classifier: Topic :: Utilities
Classifier: Topic :: Communications :: Email
Classifier: Topic :: Communications :: Email :: Post-Office :: IMAP
